opprint.py
opprint-1.0.3.dist-info/LICENSE
opprint-1.0.3.dist-info/METADATA
opprint-1.0.3.dist-info/WHEEL
opprint-1.0.3.dist-info/RECORD
